cornfig
