Metadata-Version: 1.0
Name: cornfig
Version: 0.3
Summary: applies cornfiguration from cloud metadata.
Home-page: http://github.com/echohead/cornfig
Author: echohead
Author-email: tim.miller.0@gmail.com
License: UNKNOWN
Platform: UNKNOWN
